LICENSE
MANIFEST.in
README.md
requirements.txt
setup.py
glycogenius/LICENSE.py
glycogenius/Parameters_Template.py
glycogenius/__init__.py
glycogenius/__main__.py
glycogenius.egg-info/PKG-INFO
glycogenius.egg-info/SOURCES.txt
glycogenius.egg-info/dependency_links.txt
glycogenius.egg-info/entry_points.txt
glycogenius.egg-info/requires.txt
glycogenius.egg-info/top_level.txt
glycogenius/Modules/CLI.py
glycogenius/Modules/Config_Handler.py
glycogenius/Modules/Execution_Functions.py
glycogenius/Modules/File_Accessing.py
glycogenius/Modules/General_Functions.py
glycogenius/Modules/Library_Tools.py
glycogenius/Modules/__init__.py
glycogenius/Modules/core.py