Metadata-Version: 2.1
Name: glycogenius
Version: 1.3.2
Summary: GlycoGenius is an all-in-one solution for data analysis of glycomics data.
Author: Hector Franco Loponte
Author-email: hectorfloponte@gmail.com
Classifier: Programming Language :: Python :: 3
Classifier: License :: OSI Approved :: GNU General Public License v3 or later (GPLv3+)
Classifier: Operating System :: OS Independent
Requires-Python: >=3.6
License-File: LICENSE
Requires-Dist: pandas==2.2.3
Requires-Dist: scipy==1.14.1
Requires-Dist: pyteomics==4.7.5
Requires-Dist: dill==0.3.9
Requires-Dist: numpy==1.26.4
Requires-Dist: lxml==5.3.0
Requires-Dist: openpyxl==3.1.5
Requires-Dist: setuptools
Requires-Dist: xlsxwriter==3.2.0
